{
    "WFWorkflowMinimumClientVersionString": "900",
    "WFWorkflowMinimumClientVersion": 900,
    "WFWorkflowIcon": {
        "WFWorkflowIconStartColor": 2846468607,
        "WFWorkflowIconGlyphNumber": 59681
    },
    "WFWorkflowClientVersion": "3036.0.4.2",
    "WFWorkflowOutputContentItemClasses": [
        "WFStringContentItem"
    ],
    "WFWorkflowHasOutputFallback": false,
    "WFWorkflowActions": [
        {
            "WFWorkflowActionIdentifier": "is.workflow.actions.conditional",
            "WFWorkflowActionParameters": {
                "WFInput": {
                    "Type": "Variable",
                    "Variable": {
                        "Value": {
                            "Type": "ExtensionInput"
                        },
                        "WFSerializationType": "WFTextTokenAttachment"
                    }
                },
                "WFControlFlowMode": 0,
                "GroupingIdentifier": "9A020F12-7584-4F71-A22A-6E9EB4535435",
                "WFCondition": 100
            }
        },
        {
            "WFWorkflowActionIdentifier": "is.workflow.actions.detect.date",
            "WFWorkflowActionParameters": {
                "WFInput": {
                    "Value": {
                        "Type": "ExtensionInput"
                    },
                    "WFSerializationType": "WFTextTokenAttachment"
                },
                "UUID": "4A01DA9B-0FF0-453F-AE19-F6D52404D70A"
            }
        },
        {
            "WFWorkflowActionIdentifier": "is.workflow.actions.conditional",
            "WFWorkflowActionParameters": {
                "GroupingIdentifier": "9A020F12-7584-4F71-A22A-6E9EB4535435",
                "WFControlFlowMode": 1
            }
        },
        {
            "WFWorkflowActionIdentifier": "is.workflow.actions.date",
            "WFWorkflowActionParameters": {
                "WFDateActionDate": "Today",
                "WFDateActionMode": "Specified Date",
                "UUID": "1367F3F9-C248-4CDD-9B9A-2779A8612A45"
            }
        },
        {
            "WFWorkflowActionIdentifier": "is.workflow.actions.conditional",
            "WFWorkflowActionParameters": {
                "WFControlFlowMode": 2,
                "GroupingIdentifier": "9A020F12-7584-4F71-A22A-6E9EB4535435",
                "UUID": "BF043C19-8509-4E2D-A78A-930EBCFB6C90"
            }
        },
        {
            "WFWorkflowActionIdentifier": "is.workflow.actions.comment",
            "WFWorkflowActionParameters": {
                "WFCommentActionText": "Set Locale to UK to use Monday as the first day of the week instead of Sunday"
            }
        },
        {
            "WFWorkflowActionIdentifier": "is.workflow.actions.format.date",
            "WFWorkflowActionParameters": {
                "WFDateFormatStyle": "Custom",
                "WFDateFormat": "ww",
                "UUID": "59E73EA9-D89F-43BF-9274-9A6372E459E1",
                "WFLocale": "en_GB",
                "WFDate": {
                    "Value": {
                        "string": "￼",
                        "attachmentsByRange": {
                            "{0, 1}": {
                                "OutputUUID": "BF043C19-8509-4E2D-A78A-930EBCFB6C90",
                                "Type": "ActionOutput",
                                "OutputName": "If Result"
                            }
                        }
                    },
                    "WFSerializationType": "WFTextTokenString"
                }
            }
        },
        {
            "WFWorkflowActionIdentifier": "is.workflow.actions.setvariable",
            "WFWorkflowActionParameters": {
                "WFInput": {
                    "Value": {
                        "OutputUUID": "59E73EA9-D89F-43BF-9274-9A6372E459E1",
                        "Type": "ActionOutput",
                        "OutputName": "Formatted Date"
                    },
                    "WFSerializationType": "WFTextTokenAttachment"
                },
                "WFVariableName": "Week Number"
            }
        },
        {
            "WFWorkflowActionIdentifier": "is.workflow.actions.output",
            "WFWorkflowActionParameters": {
                "WFOutput": {
                    "Value": {
                        "string": "￼",
                        "attachmentsByRange": {
                            "{0, 1}": {
                                "VariableName": "Week Number",
                                "Type": "Variable"
                            }
                        }
                    },
                    "WFSerializationType": "WFTextTokenString"
                }
            }
        }
    ],
    "WFWorkflowInputContentItemClasses": [
        "WFDateContentItem"
    ],
    "WFWorkflowImportQuestions": [
        {
            "Category": "Parameter",
            "ParameterKey": "WFTextActionText",
            "ActionIndex": 0,
            "Text": "What is your first name?",
            "DefaultValue": ""
        }
    ],
    "WFWorkflowTypes": [
        "NCWidget"
    ],
    "WFQuickActionSurfaces": [],
    "WFWorkflowHasShortcutInputVariables": true
}