{
    "category": "Weather",
    "downloadLink": "https://www.icloud.com/attachment/?u=https%3A%2F%2Fcvws.icloud-content.com%2FB%2FASmDnuX8LudoOpiyoRfTP0qLVV9zAQn_IXdiiskBdEYa5eCzBVoxc8gi%2F%24%7Bf%7D%3Fo%3DAmbpTfGm5mkgTRQjTJjDoJ4wbKTB9oJz6P38c0sjwwQO%26v%3D1%26x%3D3%26a%3DCAog9abAcsQ4dppOEmqlkqX_5IQYIgyBtqYYEnZmkrhEJGYSbRDYibSUnTIY2Jmv6KYyIgEAUgSLVV9zWgQxc8giaib8am67N4HE1HRB0vtSkj0cQo-1-u9Qeluq2nGMyj858W87ozAp7HImxMp5ayVMdVApMiUbqqPzPhDRxL7BqS35A6qF8X7DWBvwGNwUmOM%26e%3D1728406342%26fl%3D%26r%3DCF096934-DB47-4FE1-B55A-6669524535F4-1%26k%3D%24%7Buk%7D%26ckc%3Dcom.apple.clouddocs%26ckz%3Dcom.apple.CloudDocs%26p%3D108%26s%3D0Z-f9hV7du_YhfYIc_k_Nydsbc0&uk=Q4Q_v-g9KbQj3HOj_AcLrg&f=isSunUp%3F.shortcut&sz=27298",
    "sourceCode": "{\"WFWorkflowMinimumClientVersionString\":\"900\",\"WFWorkflowMinimumClientVersion\":900,\"WFWorkflowIcon\":{\"WFWorkflowIconStartColor\":2846468607,\"WFWorkflowIconGlyphNumber\":61440},\"WFWorkflowClientVersion\":\"2605.0.5\",\"WFWorkflowOutputContentItemClasses\":[\"WFBooleanContentItem\"],\"WFWorkflowHasOutputFallback\":false,\"WFWorkflowActions\":[{\"WFWorkflowActionIdentifier\":\"is.workflow.actions.weather.currentconditions\",\"WFWorkflowActionParameters\":{\"UUID\":\"1DEDE8F5-90C2-4550-9E96-5BD4BE1DC6B2\"}},{\"WFWorkflowActionIdentifier\":\"is.workflow.actions.conditional\",\"WFWorkflowActionParameters\":{\"WFDate\":{\"Value\":{\"Type\":\"ActionOutput\",\"OutputName\":\"Weather Conditions\",\"OutputUUID\":\"1DEDE8F5-90C2-4550-9E96-5BD4BE1DC6B2\",\"Aggrandizements\":[{\"Type\":\"WFPropertyVariableAggrandizement\",\"PropertyName\":\"Sunrise Time\"}]},\"WFSerializationType\":\"WFTextTokenAttachment\"},\"WFInput\":{\"Type\":\"Variable\",\"Variable\":{\"Value\":{\"Type\":\"CurrentDate\"},\"WFSerializationType\":\"WFTextTokenAttachment\"}},\"WFAnotherDate\":{\"Value\":{\"Type\":\"ActionOutput\",\"OutputName\":\"Weather Conditions\",\"OutputUUID\":\"1DEDE8F5-90C2-4550-9E96-5BD4BE1DC6B2\",\"Aggrandizements\":[{\"Type\":\"WFPropertyVariableAggrandizement\",\"PropertyName\":\"Sunset Time\"}]},\"WFSerializationType\":\"WFTextTokenAttachment\"},\"WFControlFlowMode\":0,\"GroupingIdentifier\":\"A1296859-C0CC-49E6-9873-15004443E518\",\"WFCondition\":1003}},{\"WFWorkflowActionIdentifier\":\"is.workflow.actions.gettext\",\"WFWorkflowActionParameters\":{\"WFTextActionText\":\"Yes\",\"UUID\":\"3E820727-766A-4AC0-9E28-1D520CD14078\"}},{\"WFWorkflowActionIdentifier\":\"is.workflow.actions.conditional\",\"WFWorkflowActionParameters\":{\"GroupingIdentifier\":\"A1296859-C0CC-49E6-9873-15004443E518\",\"WFControlFlowMode\":1}},{\"WFWorkflowActionIdentifier\":\"is.workflow.actions.gettext\",\"WFWorkflowActionParameters\":{\"WFTextActionText\":\"No\"}},{\"WFWorkflowActionIdentifier\":\"is.workflow.actions.conditional\",\"WFWorkflowActionParameters\":{\"WFControlFlowMode\":2,\"GroupingIdentifier\":\"A1296859-C0CC-49E6-9873-15004443E518\",\"UUID\":\"10E9A647-ECDC-4FA1-A3EC-B3579AFD9CC3\"}},{\"WFWorkflowActionIdentifier\":\"is.workflow.actions.output\",\"WFWorkflowActionParameters\":{\"WFOutput\":{\"Value\":{\"string\":\"￼\",\"attachmentsByRange\":{\"{0, 1}\":{\"Type\":\"ActionOutput\",\"OutputName\":\"If Result\",\"OutputUUID\":\"10E9A647-ECDC-4FA1-A3EC-B3579AFD9CC3\",\"Aggrandizements\":[{\"Type\":\"WFCoercionVariableAggrandizement\",\"CoercionItemClass\":\"WFBooleanContentItem\"}]}}},\"WFSerializationType\":\"WFTextTokenString\"}}}],\"WFWorkflowInputContentItemClasses\":[\"WFAppContentItem\",\"WFAppStoreAppContentItem\",\"WFArticleContentItem\",\"WFContactContentItem\",\"WFDateContentItem\",\"WFEmailAddressContentItem\",\"WFFolderContentItem\",\"WFGenericFileContentItem\",\"WFImageContentItem\",\"WFiTunesProductContentItem\",\"WFLocationContentItem\",\"WFDCMapsLinkContentItem\",\"WFAVAssetContentItem\",\"WFPDFContentItem\",\"WFPhoneNumberContentItem\",\"WFRichTextContentItem\",\"WFSafariWebPageContentItem\",\"WFStringContentItem\",\"WFURLContentItem\"],\"WFWorkflowImportQuestions\":[],\"WFWorkflowTypes\":[],\"WFQuickActionSurfaces\":[],\"WFWorkflowHasShortcutInputVariables\":false}",
    "version": "",
    "description": "",
    "shortcutName": "isSunUp?",
    "actionCount": "7"
}