{
    "category": "Google Sheets API",
    "downloadLink": "https://www.icloud.com/attachment/?u=https%3A%2F%2Fcvws.icloud-content.com%2FB%2FAfIbb1W1Hc_lk-TryeqZt-hgexcxARVLuOKKY-0FhCTHKn4NpEtEPRKQ%2F%24%7Bf%7D%3Fo%3DAktaloYxcTR0sGdvwXi5-1uf7L57QpTr3-QwI5W60c2A%26v%3D1%26x%3D3%26a%3DCAogU6B73TbJ3nVTTCZL8itDBGLkNuID2_EURfPrjBivN0ESbRDturzyozIY7cq3xq0yIgEAUgRgexcxWgREPRKQaiZRps1CyhzEnIGMJdu8lU3SQICapV5Vajla3jZXDYz5G0MqXxrasXImkGxEj5t_xP-SAElshfIirhn6C7Z3K2jDAJC82MWqKYkhL82AXfM%26e%3D1730214225%26fl%3D%26r%3D5C7BBE45-24D4-4837-8615-2C4903F3D30F-1%26k%3D%24%7Buk%7D%26ckc%3Dcom.apple.clouddocs%26ckz%3Dcom.apple.CloudDocs%26p%3D108%26s%3DYG_eEUILPV-vnoeId9ZJqvtbW58&uk=HC18xVmblbYD-wur1C_Bjw&f=Hide%20Sheet.shortcut&sz=27432",
    "sourceCode": "{\"WFWorkflowMinimumClientVersionString\":\"900\",\"WFWorkflowMinimumClientVersion\":900,\"WFWorkflowIcon\":{\"WFWorkflowIconStartColor\":2846468607,\"WFWorkflowIconGlyphNumber\":61440},\"WFWorkflowClientVersion\":\"2605.0.5\",\"WFWorkflowOutputContentItemClasses\":[],\"WFWorkflowHasOutputFallback\":false,\"WFWorkflowActions\":[{\"WFWorkflowActionIdentifier\":\"is.workflow.actions.comment\",\"WFWorkflowActionParameters\":{\"WFCommentActionText\":\"https:\\/\\/developers.google.com\\/sheets\\/api\\/reference\\/rest\\/v4\\/spreadsheets\\/request#updatesheetpropertiesrequest\"}},{\"WFWorkflowActionIdentifier\":\"is.workflow.actions.detect.dictionary\",\"WFWorkflowActionParameters\":{\"WFInput\":{\"Value\":{\"Type\":\"ExtensionInput\"},\"WFSerializationType\":\"WFTextTokenAttachment\"},\"UUID\":\"A1F87235-63A9-4471-AE92-DE3A208A436D\"}},{\"WFWorkflowActionIdentifier\":\"is.workflow.actions.gettext\",\"WFWorkflowActionParameters\":{\"WFTextActionText\":{\"Value\":{\"string\":\"{\\n  \\\"requests\\\": {\\n    \\\"updateSheetProperties\\\": {\\n      \\\"properties\\\": {\\n        \\\"sheetId\\\": \\\"￼\\\",\\n        \\\"hidden\\\": \\\"True\\\"\\n      },\\n      \\\"fields\\\": \\\"hidden\\\"\\n    }\\n  }\\n}\",\"attachmentsByRange\":{\"{91, 1}\":{\"Type\":\"ActionOutput\",\"OutputName\":\"Dictionary\",\"OutputUUID\":\"A1F87235-63A9-4471-AE92-DE3A208A436D\",\"Aggrandizements\":[{\"Type\":\"WFDictionaryValueVariableAggrandizement\",\"DictionaryKey\":\"sheetId\"}]}}},\"WFSerializationType\":\"WFTextTokenString\"},\"CustomOutputName\":\"requestBody\",\"UUID\":\"8B5BF501-5B63-445C-921F-CC4016F82D76\"}},{\"WFWorkflowActionIdentifier\":\"is.workflow.actions.dictionary\",\"WFWorkflowActionParameters\":{\"WFItems\":{\"Value\":{\"WFDictionaryFieldValueItems\":[{\"WFItemType\":0,\"WFKey\":{\"Value\":{\"string\":\"spreadsheetId\"},\"WFSerializationType\":\"WFTextTokenString\"},\"WFValue\":{\"Value\":{\"string\":\"￼\",\"attachmentsByRange\":{\"{0, 1}\":{\"Type\":\"ActionOutput\",\"OutputName\":\"Dictionary\",\"OutputUUID\":\"A1F87235-63A9-4471-AE92-DE3A208A436D\",\"Aggrandizements\":[{\"Type\":\"WFDictionaryValueVariableAggrandizement\",\"DictionaryKey\":\"spreadsheetId\"}]}}},\"WFSerializationType\":\"WFTextTokenString\"}},{\"WFItemType\":0,\"WFKey\":{\"Value\":{\"string\":\"requestBody\"},\"WFSerializationType\":\"WFTextTokenString\"},\"WFValue\":{\"Value\":{\"string\":\"￼\",\"attachmentsByRange\":{\"{0, 1}\":{\"OutputUUID\":\"8B5BF501-5B63-445C-921F-CC4016F82D76\",\"Type\":\"ActionOutput\",\"OutputName\":\"requestBody\"}}},\"WFSerializationType\":\"WFTextTokenString\"}}]},\"WFSerializationType\":\"WFDictionaryFieldValue\"},\"UUID\":\"93D557C1-8C01-470C-B941-E15F8FFB41BF\"}},{\"WFWorkflowActionIdentifier\":\"is.workflow.actions.runworkflow\",\"WFWorkflowActionParameters\":{\"WFInput\":{\"Value\":{\"OutputUUID\":\"93D557C1-8C01-470C-B941-E15F8FFB41BF\",\"Type\":\"ActionOutput\",\"OutputName\":\"Dictionary\"},\"WFSerializationType\":\"WFTextTokenAttachment\"},\"WFWorkflow\":{\"workflowIdentifier\":\"62665609-710F-4ADF-B59D-D4B62A9348EE\",\"workflowName\":\"Batch Update Spreadsheet Cells\",\"isSelf\":false},\"UUID\":\"7C45D47D-2B9C-4BB1-BA46-EA87B7579C57\",\"WFWorkflowName\":\"Batch Update Spreadsheet Cells\"}}],\"WFWorkflowInputContentItemClasses\":[\"WFStringContentItem\"],\"WFWorkflowImportQuestions\":[],\"WFWorkflowTypes\":[\"Watch\"],\"WFQuickActionSurfaces\":[],\"WFWorkflowHasShortcutInputVariables\":true}",
    "version": "",
    "description": "",
    "shortcutName": "Hide Sheet",
    "actionCount": "5"
}