{
    "category": "Apps",
    "downloadLink": "https://www.icloud.com/attachment/?u=https%3A%2F%2Fcvws.icloud-content.com%2FB%2FAfaE4K1SS2ix7MKy2MjY9Q9tkkJ1AeoXy2TdRdjpmX9wwZjOvndoj4Y8%2F%24%7Bf%7D%3Fo%3DApeaocJ1lwEgaj2Dc-PMzDY-A_E0AB2xeu75n0WWkMnB%26v%3D1%26x%3D3%26a%3DCAogk1Nz8zXVos1hCwECXiIswmme_9S3ufXYV3GHfZxN7xYSbRDLmeDlkTIYy6nbuZsyIgEAUgRtkkJ1WgRoj4Y8aiab18X5tL9Z7_857BIxztKB5Rx4PE5irtFmJ8sxLqG39GwXCOZX_nImDcjUXlONTeS0-zgnEjUT8YDfwk9HGOol1B3NuBNBP8GWxJWVmd8%26e%3D1725355709%26fl%3D%26r%3D3842D44D-6FC9-4061-9F92-D897A1B48E8C-1%26k%3D%24%7Buk%7D%26ckc%3Dcom.apple.clouddocs%26ckz%3Dcom.apple.CloudDocs%26p%3D108%26s%3D73jjrtEfWNPOx5nTd6Et2JxH5r8&uk=npOFJaF5j4fJTDLLvcRANg&f=ALDI%20TALK.shortcut&sz=26993",
    "sourceCode": "{\"WFWorkflowMinimumClientVersionString\":\"900\",\"WFWorkflowMinimumClientVersion\":900,\"WFWorkflowIcon\":{\"WFWorkflowIconStartColor\":2846468607,\"WFWorkflowIconGlyphNumber\":61440},\"WFWorkflowClientVersion\":\"2605.0.5\",\"WFWorkflowOutputContentItemClasses\":[\"WFiTunesProductContentItem\",\"WFAVAssetContentItem\",\"WFStringContentItem\",\"WFSafariWebPageContentItem\",\"WFRichTextContentItem\",\"WFPhotoMediaContentItem\",\"WFURLContentItem\",\"WFPDFContentItem\",\"WFPhoneNumberContentItem\",\"WFLocationContentItem\",\"WFImageContentItem\",\"WFAppStoreAppContentItem\",\"WFGenericFileContentItem\",\"WFEmailAddressContentItem\",\"WFDateContentItem\",\"WFContactContentItem\",\"WFArticleContentItem\",\"WFAppContentItem\",\"WFMKMapItemContentItem\",\"WFFolderContentItem\",\"WFDCMapsLinkContentItem\"],\"WFWorkflowHasOutputFallback\":false,\"WFWorkflowActions\":[{\"WFWorkflowActionIdentifier\":\"is.workflow.actions.openapp\",\"WFWorkflowActionParameters\":{\"WFSelectedApp\":{\"BundleIdentifier\":\"de.eplus.mappecc.client.ios.alditalk\",\"Name\":\"ALDI TALK\",\"TeamIdentifier\":\"7DE4JW22H4\"},\"WFAppIdentifier\":\"de.eplus.mappecc.client.ios.alditalk\",\"UUID\":\"685DA08A-AD50-466B-B893-916C30169B63\"}},{\"WFWorkflowActionIdentifier\":\"is.workflow.actions.output\",\"WFWorkflowActionParameters\":{\"WFOutput\":{\"Value\":{\"string\":\"￼\",\"attachmentsByRange\":{\"{0, 1}\":{\"OutputUUID\":\"685DA08A-AD50-466B-B893-916C30169B63\",\"Type\":\"ActionOutput\",\"OutputName\":\"App\"}}},\"WFSerializationType\":\"WFTextTokenString\"}}}],\"WFWorkflowInputContentItemClasses\":[\"WFAppContentItem\",\"WFAppStoreAppContentItem\",\"WFArticleContentItem\",\"WFContactContentItem\",\"WFDateContentItem\",\"WFEmailAddressContentItem\",\"WFFolderContentItem\",\"WFGenericFileContentItem\",\"WFImageContentItem\",\"WFiTunesProductContentItem\",\"WFLocationContentItem\",\"WFDCMapsLinkContentItem\",\"WFAVAssetContentItem\",\"WFPDFContentItem\",\"WFPhoneNumberContentItem\",\"WFRichTextContentItem\",\"WFSafariWebPageContentItem\",\"WFStringContentItem\",\"WFURLContentItem\"],\"WFWorkflowImportQuestions\":[],\"WFWorkflowTypes\":[\"Watch\"],\"WFQuickActionSurfaces\":[],\"WFWorkflowHasShortcutInputVariables\":false}",
    "version": "",
    "description": "",
    "shortcutName": "ALDI TALK",
    "actionCount": "2"
}