<?xml version="1.0" encoding="UTF-8"?>
<!DOCTYPE plist PUBLIC "-//Apple//DTD PLIST 1.0//EN" "http://www.apple.com/DTDs/PropertyList-1.0.dtd">
<plist version="1.0">
<dict>
	<key>WFQuickActionSurfaces</key>
	<array/>
	<key>WFWorkflowActions</key>
	<array>
		<dict>
			<key>WFWorkflowActionIdentifier</key>
			<string>is.workflow.actions.runworkflow</string>
			<key>WFWorkflowActionParameters</key>
			<dict>
				<key>UUID</key>
				<string>F0A33F0A-546D-449E-A062-14CFBC848A31</string>
				<key>WFWorkflow</key>
				<dict>
					<key>isSelf</key>
					<false/>
					<key>workflowIdentifier</key>
					<string>AF6BD325-062A-4011-AC89-27EA01E9EFC3</string>
					<key>workflowName</key>
					<string>Go to WiFi Setting</string>
				</dict>
				<key>WFWorkflowName</key>
				<string>Go to WiFi Setting</string>
			</dict>
		</dict>
		<dict>
			<key>WFWorkflowActionIdentifier</key>
			<string>is.workflow.actions.wifi.set</string>
			<key>WFWorkflowActionParameters</key>
			<dict/>
		</dict>
	</array>
	<key>WFWorkflowClientVersion</key>
	<string>3036.0.4.2</string>
	<key>WFWorkflowHasOutputFallback</key>
	<false/>
	<key>WFWorkflowHasShortcutInputVariables</key>
	<false/>
	<key>WFWorkflowIcon</key>
	<dict>
		<key>WFWorkflowIconGlyphNumber</key>
		<integer>61440</integer>
		<key>WFWorkflowIconStartColor</key>
		<integer>2846468607</integer>
	</dict>
	<key>WFWorkflowImportQuestions</key>
	<array/>
	<key>WFWorkflowInputContentItemClasses</key>
	<array>
		<string>WFStringContentItem</string>
	</array>
	<key>WFWorkflowMinimumClientVersion</key>
	<integer>900</integer>
	<key>WFWorkflowMinimumClientVersionString</key>
	<string>900</string>
	<key>WFWorkflowOutputContentItemClasses</key>
	<array/>
	<key>WFWorkflowTypes</key>
	<array/>
</dict>
</plist>
