{
    "category": "Build URLs",
    "downloadLink": "https://www.icloud.com/attachment/?u=https%3A%2F%2Fcvws.icloud-content.com%2FB%2FAVMEITZ1ucb5ULoP8utEZLVjQpf3ARR-mgipvn1iWlZwQ8gDlSNdQmJQ%2F%24%7Bf%7D%3Fo%3DAsD5mBetpaOuN2h96R1cT5tG3jMaobsEylYnoy5zyj-0%26v%3D1%26x%3D3%26a%3DCAogpZlS67bnxJJe0zUnV3eQiDpMEPGsl4Z0YuDJ3Kc-G54SbRDpxrfyozIY6dayxq0yIgEAUgRjQpf3WgRdQmJQaiYNxpu2UOXa87PX5dsRIhDd8PvgU9yg-dFcNj5JUju9Z0GjLwXrkHImUK_-E347Nnbhd7eoGbfgG3_FFQqul6z08SgqXYWVxrF8TTD9cXs%26e%3D1730214144%26fl%3D%26r%3D71FA3217-E688-4464-98C7-1FFAED02A857-1%26k%3D%24%7Buk%7D%26ckc%3Dcom.apple.clouddocs%26ckz%3Dcom.apple.CloudDocs%26p%3D108%26s%3DhnHH_lCYCgvFK16OXjzqpfoxDig&uk=R-2bWF64Z5pYJ3J7hvnbrA&f=Build%20Google%20Search%20URL.shortcut&sz=26865",
    "sourceCode": "{\"WFWorkflowMinimumClientVersionString\":\"1113\",\"WFWorkflowMinimumClientVersion\":1113,\"WFWorkflowIcon\":{\"WFWorkflowIconStartColor\":2846468607,\"WFWorkflowIconGlyphNumber\":59685},\"WFWorkflowClientVersion\":\"2605.0.5\",\"WFWorkflowOutputContentItemClasses\":[\"WFURLContentItem\"],\"WFWorkflowHasOutputFallback\":false,\"WFWorkflowNoInputBehavior\":{\"Name\":\"WFWorkflowNoInputBehaviorAskForInput\",\"Parameters\":{\"ItemClass\":\"WFStringContentItem\"}},\"WFWorkflowActions\":[{\"WFWorkflowActionIdentifier\":\"is.workflow.actions.text.combine\",\"WFWorkflowActionParameters\":{\"text\":{\"Value\":{\"string\":\"￼\",\"attachmentsByRange\":{\"{0, 1}\":{\"Type\":\"ExtensionInput\"}}},\"WFSerializationType\":\"WFTextTokenString\"},\"UUID\":\"6CA120D2-4D2A-4837-8D57-20BFA6106A91\"}},{\"WFWorkflowActionIdentifier\":\"is.workflow.actions.urlencode\",\"WFWorkflowActionParameters\":{\"WFInput\":{\"Value\":{\"string\":\"￼\",\"attachmentsByRange\":{\"{0, 1}\":{\"OutputUUID\":\"6CA120D2-4D2A-4837-8D57-20BFA6106A91\",\"Type\":\"ActionOutput\",\"OutputName\":\"Combined Text\"}}},\"WFSerializationType\":\"WFTextTokenString\"},\"UUID\":\"6D664EAE-7D35-426C-AC7F-00201485701A\"}},{\"WFWorkflowActionIdentifier\":\"is.workflow.actions.url\",\"WFWorkflowActionParameters\":{\"WFURLActionURL\":{\"Value\":{\"string\":\"https:\\/\\/www.google.com\\/search?q=￼\",\"attachmentsByRange\":{\"{32, 1}\":{\"OutputUUID\":\"6D664EAE-7D35-426C-AC7F-00201485701A\",\"Type\":\"ActionOutput\",\"OutputName\":\"URL Encoded Text\"}}},\"WFSerializationType\":\"WFTextTokenString\"},\"UUID\":\"0B0E2AA4-E85E-471D-9E52-B3E2D5A4C806\"}},{\"WFWorkflowActionIdentifier\":\"is.workflow.actions.output\",\"WFWorkflowActionParameters\":{\"WFOutput\":{\"Value\":{\"string\":\"￼\",\"attachmentsByRange\":{\"{0, 1}\":{\"OutputUUID\":\"0B0E2AA4-E85E-471D-9E52-B3E2D5A4C806\",\"Type\":\"ActionOutput\",\"OutputName\":\"URL\"}}},\"WFSerializationType\":\"WFTextTokenString\"}}}],\"WFWorkflowInputContentItemClasses\":[\"WFStringContentItem\"],\"WFWorkflowImportQuestions\":[],\"WFQuickActionSurfaces\":[],\"WFWorkflowTypes\":[],\"WFWorkflowHasShortcutInputVariables\":true}",
    "version": "",
    "description": "",
    "shortcutName": "Build Google Search URL",
    "actionCount": "5"
}