{
    "WFWorkflowMinimumClientVersionString": "900",
    "WFWorkflowMinimumClientVersion": 900,
    "WFWorkflowIcon": {
        "WFWorkflowIconStartColor": 2846468607,
        "WFWorkflowIconGlyphNumber": 61440
    },
    "WFWorkflowClientVersion": "3107.0.8.2",
    "WFWorkflowOutputContentItemClasses": [],
    "WFWorkflowHasOutputFallback": false,
    "WFWorkflowActions": [
        {
            "WFWorkflowActionIdentifier": "is.workflow.actions.runworkflow",
            "WFWorkflowActionParameters": {
                "WFWorkflow": {
                    "workflowIdentifier": "110E82F0-DEA6-433B-89B1-2BB54B3070A6",
                    "workflowName": "Obsidian - Disable Community Plugins on Mobile",
                    "isSelf": false
                },
                "WFWorkflowName": "Obsidian - Disable Community Plugins on Mobile",
                "UUID": "4DA2E532-4371-458D-926B-91240800DCDD"
            }
        },
        {
            "WFWorkflowActionIdentifier": "AsheKube.app.a-Shell.ExecuteCommandIntent",
            "WFWorkflowActionParameters": {
                "command": [
                    "jump obsidian-icloud",
                    "rm -rf \"Second-Brain/.obsidian-mobile\"",
                    "cp -r \"Second-Brain/.obsidian\" \"Second-Brain/.obsidian-mobile\""
                ],
                "UUID": "65CF399E-A258-4083-B9FB-D934729D297A",
                "openWindow": "close",
                "ShowWhenRun": false
            }
        },
        {
            "WFWorkflowActionIdentifier": "is.workflow.actions.dictionary",
            "WFWorkflowActionParameters": {
                "WFItems": {
                    "Value": {
                        "WFDictionaryFieldValueItems": [
                            {
                                "WFItemType": 1,
                                "WFKey": {
                                    "Value": {
                                        "string": "plugins/obsidian-minimal-settings/data.json"
                                    },
                                    "WFSerializationType": "WFTextTokenString"
                                },
                                "WFValue": {
                                    "Value": {
                                        "Value": {
                                            "WFDictionaryFieldValueItems": [
                                                {
                                                    "WFItemType": 4,
                                                    "WFKey": {
                                                        "Value": {
                                                            "string": "focusMode"
                                                        },
                                                        "WFSerializationType": "WFTextTokenString"
                                                    },
                                                    "WFValue": {
                                                        "Value": false,
                                                        "WFSerializationType": "WFNumberSubstitutableState"
                                                    }
                                                }
                                            ]
                                        },
                                        "WFSerializationType": "WFDictionaryFieldValue"
                                    },
                                    "WFSerializationType": "WFDictionaryFieldValue"
                                }
                            },
                            {
                                "WFItemType": 1,
                                "WFKey": {
                                    "Value": {
                                        "string": "app.json"
                                    },
                                    "WFSerializationType": "WFTextTokenString"
                                },
                                "WFValue": {
                                    "Value": {
                                        "Value": {
                                            "WFDictionaryFieldValueItems": [
                                                {
                                                    "WFItemType": 4,
                                                    "WFKey": {
                                                        "Value": {
                                                            "string": "readableLineLength"
                                                        },
                                                        "WFSerializationType": "WFTextTokenString"
                                                    },
                                                    "WFValue": {
                                                        "Value": false,
                                                        "WFSerializationType": "WFNumberSubstitutableState"
                                                    }
                                                }
                                            ]
                                        },
                                        "WFSerializationType": "WFDictionaryFieldValue"
                                    },
                                    "WFSerializationType": "WFDictionaryFieldValue"
                                }
                            },
                            {
                                "WFItemType": 1,
                                "WFKey": {
                                    "Value": {
                                        "string": "core-plugins.json"
                                    },
                                    "WFSerializationType": "WFTextTokenString"
                                },
                                "WFValue": {
                                    "Value": {
                                        "Value": {
                                            "WFDictionaryFieldValueItems": [
                                                {
                                                    "WFItemType": 4,
                                                    "WFKey": {
                                                        "Value": {
                                                            "string": "page-preview"
                                                        },
                                                        "WFSerializationType": "WFTextTokenString"
                                                    },
                                                    "WFValue": {
                                                        "Value": false,
                                                        "WFSerializationType": "WFNumberSubstitutableState"
                                                    }
                                                }
                                            ]
                                        },
                                        "WFSerializationType": "WFDictionaryFieldValue"
                                    },
                                    "WFSerializationType": "WFDictionaryFieldValue"
                                }
                            }
                        ]
                    },
                    "WFSerializationType": "WFDictionaryFieldValue"
                },
                "UUID": "D4F1B6C3-E785-45F9-97CC-69AB92E1A0EE"
            }
        },
        {
            "WFWorkflowActionIdentifier": "is.workflow.actions.runworkflow",
            "WFWorkflowActionParameters": {
                "WFInput": {
                    "Value": {
                        "OutputUUID": "D4F1B6C3-E785-45F9-97CC-69AB92E1A0EE",
                        "Type": "ActionOutput",
                        "OutputName": "Dictionary"
                    },
                    "WFSerializationType": "WFTextTokenAttachment"
                },
                "WFWorkflow": {
                    "workflowIdentifier": "7B4AF74D-8B18-41C2-AD8E-A67EBC8F8729",
                    "workflowName": "Obsidian - Set App Setting Value for Mobile",
                    "isSelf": false
                },
                "UUID": "33F274A9-2A2B-429D-B76C-2EEE1C0884B0",
                "WFWorkflowName": "Obsidian - Set App Setting Value for Mobile"
            }
        }
    ],
    "WFWorkflowInputContentItemClasses": [
        "WFAppContentItem",
        "WFAppStoreAppContentItem",
        "WFArticleContentItem",
        "WFContactContentItem",
        "WFDateContentItem",
        "WFEmailAddressContentItem",
        "WFFolderContentItem",
        "WFGenericFileContentItem",
        "WFImageContentItem",
        "WFiTunesProductContentItem",
        "WFLocationContentItem",
        "WFDCMapsLinkContentItem",
        "WFAVAssetContentItem",
        "WFPDFContentItem",
        "WFPhoneNumberContentItem",
        "WFRichTextContentItem",
        "WFSafariWebPageContentItem",
        "WFStringContentItem",
        "WFURLContentItem"
    ],
    "WFWorkflowImportQuestions": [],
    "WFWorkflowTypes": [],
    "WFQuickActionSurfaces": [],
    "WFWorkflowHasShortcutInputVariables": false
}