{
    "category": "Siri",
    "downloadLink": "https://www.icloud.com/attachment/?u=https%3A%2F%2Fcvws.icloud-content.com%2FB%2FAVXRUhf2N8TO9Wh06hIvA6NRVoS8AauOZBgtZkuxAGPYUr04lLgdJb40%2F%24%7Bf%7D%3Fo%3DAicXDsP-WlNTtJFQ_aokal5J1Kf9LH0mVUayZZ730KFC%26v%3D1%26x%3D3%26a%3DCAogz7GkEMXPDZiW5jzaKcXX8PrAmAKdwJg04p8vlH1fNrQSbRCKyavVjzIYitmmqZkyIgEAUgRRVoS8WgQdJb40aiZXRnGMWYRyUP628UY2TG-8LrsjEBpvVTnUBB3K4KsGEuFW9ACBBnImUkLD7otPHUpiB9ePV8WsL5d8NWCrDE5FuenxBpSFc1qSZXcTyUw%26e%3D1724784422%26fl%3D%26r%3DFC266597-F515-4CDE-8506-F5FA367F007D-1%26k%3D%24%7Buk%7D%26ckc%3Dcom.apple.clouddocs%26ckz%3Dcom.apple.CloudDocs%26p%3D108%26s%3Dlw-y5rty_6iNDk29oKqPQaX2-Y0&uk=KxA3TA_A6a7IVSdqJkmohw&f=%E9%87%8F%E9%AB%94%E9%87%8D.shortcut&sz=26678",
    "sourceCode": "{\"WFWorkflowMinimumClientVersionString\":\"900\",\"WFWorkflowMinimumClientVersion\":900,\"WFWorkflowIcon\":{\"WFWorkflowIconStartColor\":2846468607,\"WFWorkflowIconGlyphNumber\":61440},\"WFWorkflowClientVersion\":\"2605.0.5\",\"WFWorkflowOutputContentItemClasses\":[],\"WFWorkflowHasOutputFallback\":false,\"WFWorkflowActions\":[{\"WFWorkflowActionIdentifier\":\"is.workflow.actions.dismisssiri\",\"WFWorkflowActionParameters\":{}},{\"WFWorkflowActionIdentifier\":\"is.workflow.actions.runworkflow\",\"WFWorkflowActionParameters\":{\"WFWorkflow\":{\"workflowIdentifier\":\"B28D4CBB-6828-4642-AEA6-41F6994F5353\",\"workflowName\":\"🔢 Record Body Weight\",\"isSelf\":false},\"WFWorkflowName\":\"🔢 Record Body Weight\",\"UUID\":\"441A4419-8403-42FC-A4C0-BAE8ABC8812D\"}}],\"WFWorkflowInputContentItemClasses\":[\"WFAppStoreAppContentItem\",\"WFArticleContentItem\",\"WFContactContentItem\",\"WFDateContentItem\",\"WFEmailAddressContentItem\",\"WFGenericFileContentItem\",\"WFImageContentItem\",\"WFiTunesProductContentItem\",\"WFLocationContentItem\",\"WFDCMapsLinkContentItem\",\"WFAVAssetContentItem\",\"WFPDFContentItem\",\"WFPhoneNumberContentItem\",\"WFRichTextContentItem\",\"WFSafariWebPageContentItem\",\"WFStringContentItem\",\"WFURLContentItem\"],\"WFWorkflowImportQuestions\":[],\"WFWorkflowTypes\":[],\"WFQuickActionSurfaces\":[],\"WFWorkflowHasShortcutInputVariables\":false}",
    "version": "",
    "description": "",
    "shortcutName": "量體重",
    "actionCount": "2"
}