{
    "WFWorkflowMinimumClientVersionString": "900",
    "WFWorkflowMinimumClientVersion": 900,
    "WFWorkflowIcon": {
        "WFWorkflowIconStartColor": 2846468607,
        "WFWorkflowIconGlyphNumber": 61440
    },
    "WFWorkflowClientVersion": "3036.0.4.2",
    "WFWorkflowOutputContentItemClasses": [
        "WFStringContentItem",
        "WFContentItem",
        "WFReminderContentItem"
    ],
    "WFWorkflowHasOutputFallback": false,
    "WFWorkflowActions": [
        {
            "WFWorkflowActionIdentifier": "is.workflow.actions.comment",
            "WFWorkflowActionParameters": {
                "WFCommentActionText": "Spin Wheels"
            }
        },
        {
            "WFWorkflowActionIdentifier": "is.workflow.actions.conditional",
            "WFWorkflowActionParameters": {
                "WFInput": {
                    "Type": "Variable",
                    "Variable": {
                        "Value": {
                            "Type": "ExtensionInput"
                        },
                        "WFSerializationType": "WFTextTokenAttachment"
                    }
                },
                "WFControlFlowMode": 0,
                "GroupingIdentifier": "16598923-E53C-4139-B36E-E3028925CD02",
                "WFCondition": 100
            }
        },
        {
            "WFWorkflowActionIdentifier": "is.workflow.actions.detect.dictionary",
            "WFWorkflowActionParameters": {
                "WFInput": {
                    "Value": {
                        "Type": "ExtensionInput"
                    },
                    "WFSerializationType": "WFTextTokenAttachment"
                },
                "UUID": "0A2F6817-7408-4FA0-BBF2-5AE34B6D26D3"
            }
        },
        {
            "WFWorkflowActionIdentifier": "is.workflow.actions.getvalueforkey",
            "WFWorkflowActionParameters": {
                "WFInput": {
                    "Value": {
                        "OutputUUID": "0A2F6817-7408-4FA0-BBF2-5AE34B6D26D3",
                        "Type": "ActionOutput",
                        "OutputName": "Dictionary"
                    },
                    "WFSerializationType": "WFTextTokenAttachment"
                },
                "CustomOutputName": "topic",
                "UUID": "F6F3F58C-5BAE-4E88-A2DB-E49849610F11",
                "WFDictionaryKey": "topic"
            }
        },
        {
            "WFWorkflowActionIdentifier": "is.workflow.actions.filter.reminders",
            "WFWorkflowActionParameters": {
                "WFContentItemLimitEnabled": true,
                "UUID": "1A1D1EE3-2AF5-4523-86C1-33CDC5778353",
                "WFContentItemLimitNumber": 1,
                "WFContentItemFilter": {
                    "Value": {
                        "WFActionParameterFilterPrefix": 1,
                        "WFContentPredicateBoundedDate": false,
                        "WFActionParameterFilterTemplates": [
                            {
                                "Operator": 4,
                                "Values": {
                                    "Enumeration": {
                                        "Value": "💭 Journal Prompts",
                                        "WFSerializationType": "WFStringSubstitutableState"
                                    }
                                },
                                "Removable": true,
                                "Property": "List"
                            },
                            {
                                "Operator": 4,
                                "Values": {
                                    "Bool": false
                                },
                                "Removable": true,
                                "Property": "Is Completed"
                            },
                            {
                                "Operator": 99,
                                "Values": {
                                    "Bool": false,
                                    "String": {
                                        "Value": {
                                            "string": "￼",
                                            "attachmentsByRange": {
                                                "{0, 1}": {
                                                    "OutputUUID": "F6F3F58C-5BAE-4E88-A2DB-E49849610F11",
                                                    "Type": "ActionOutput",
                                                    "OutputName": "topic"
                                                }
                                            }
                                        },
                                        "WFSerializationType": "WFTextTokenString"
                                    }
                                },
                                "Removable": true,
                                "Property": "Title"
                            },
                            {
                                "Operator": 4,
                                "Values": {
                                    "Bool": true
                                },
                                "Removable": true,
                                "Property": "Has Subtasks"
                            }
                        ]
                    },
                    "WFSerializationType": "WFContentPredicateTableTemplate"
                }
            }
        },
        {
            "WFWorkflowActionIdentifier": "is.workflow.actions.conditional",
            "WFWorkflowActionParameters": {
                "WFInput": {
                    "Type": "Variable",
                    "Variable": {
                        "Value": {
                            "Type": "ActionOutput",
                            "OutputName": "topic",
                            "OutputUUID": "F6F3F58C-5BAE-4E88-A2DB-E49849610F11",
                            "Aggrandizements": [
                                {
                                    "PropertyUserInfo": "WFItemName",
                                    "Type": "WFPropertyVariableAggrandizement",
                                    "PropertyName": "Name"
                                }
                            ]
                        },
                        "WFSerializationType": "WFTextTokenAttachment"
                    }
                },
                "WFControlFlowMode": 0,
                "WFConditionalActionString": "Prioritization",
                "GroupingIdentifier": "4AEE5343-FB59-429E-B9A8-CB510E5C3390",
                "WFCondition": 4
            }
        },
        {
            "WFWorkflowActionIdentifier": "is.workflow.actions.getvalueforkey",
            "WFWorkflowActionParameters": {
                "WFInput": {
                    "Value": {
                        "OutputUUID": "0A2F6817-7408-4FA0-BBF2-5AE34B6D26D3",
                        "Type": "ActionOutput",
                        "OutputName": "Dictionary"
                    },
                    "WFSerializationType": "WFTextTokenAttachment"
                },
                "CustomOutputName": "todayOrTomorrow",
                "UUID": "5FD170E1-AACD-48E4-95AD-80A4349355BD",
                "WFDictionaryKey": "todayOrTomorrow"
            }
        },
        {
            "WFWorkflowActionIdentifier": "is.workflow.actions.text.replace",
            "WFWorkflowActionParameters": {
                "WFInput": {
                    "Value": {
                        "string": "￼",
                        "attachmentsByRange": {
                            "{0, 1}": {
                                "Type": "ActionOutput",
                                "OutputName": "Reminders",
                                "OutputUUID": "1A1D1EE3-2AF5-4523-86C1-33CDC5778353",
                                "Aggrandizements": [
                                    {
                                        "Type": "WFPropertyVariableAggrandizement",
                                        "PropertyName": "Subtasks"
                                    }
                                ]
                            }
                        }
                    },
                    "WFSerializationType": "WFTextTokenString"
                },
                "WFReplaceTextReplace": {
                    "Value": {
                        "string": "￼",
                        "attachmentsByRange": {
                            "{0, 1}": {
                                "OutputUUID": "5FD170E1-AACD-48E4-95AD-80A4349355BD",
                                "Type": "ActionOutput",
                                "OutputName": "todayOrTomorrow"
                            }
                        }
                    },
                    "WFSerializationType": "WFTextTokenString"
                },
                "WFReplaceTextCaseSensitive": false,
                "UUID": "F8C06762-C980-4D8F-96BF-7630CEB7AC15",
                "WFReplaceTextFind": "XXX"
            }
        },
        {
            "WFWorkflowActionIdentifier": "is.workflow.actions.conditional",
            "WFWorkflowActionParameters": {
                "GroupingIdentifier": "4AEE5343-FB59-429E-B9A8-CB510E5C3390",
                "WFControlFlowMode": 1
            }
        },
        {
            "WFWorkflowActionIdentifier": "is.workflow.actions.properties.reminders",
            "WFWorkflowActionParameters": {
                "WFInput": {
                    "Value": {
                        "OutputUUID": "1A1D1EE3-2AF5-4523-86C1-33CDC5778353",
                        "Type": "ActionOutput",
                        "OutputName": "Reminders"
                    },
                    "WFSerializationType": "WFTextTokenAttachment"
                },
                "WFContentItemPropertyName": "Subtasks",
                "UUID": "22317CC2-23AC-4B3A-BD22-E2AB7479FD60"
            }
        },
        {
            "WFWorkflowActionIdentifier": "is.workflow.actions.conditional",
            "WFWorkflowActionParameters": {
                "WFControlFlowMode": 2,
                "UUID": "ED64FBF1-104B-4A01-B109-537FC5CB7A66",
                "CustomOutputName": "listOfJournalPrompts",
                "GroupingIdentifier": "4AEE5343-FB59-429E-B9A8-CB510E5C3390"
            }
        },
        {
            "WFWorkflowActionIdentifier": "is.workflow.actions.conditional",
            "WFWorkflowActionParameters": {
                "WFInput": {
                    "Type": "Variable",
                    "Variable": {
                        "Value": {
                            "Type": "ActionOutput",
                            "OutputName": "Dictionary",
                            "OutputUUID": "0A2F6817-7408-4FA0-BBF2-5AE34B6D26D3",
                            "Aggrandizements": [
                                {
                                    "Type": "WFDictionaryValueVariableAggrandizement",
                                    "DictionaryKey": "numberOfItems"
                                }
                            ]
                        },
                        "WFSerializationType": "WFTextTokenAttachment"
                    }
                },
                "WFControlFlowMode": 0,
                "GroupingIdentifier": "0AA4CBA2-80A0-4BE4-AD79-1D0AA0CF618C",
                "WFCondition": 100
            }
        },
        {
            "WFWorkflowActionIdentifier": "is.workflow.actions.detect.number",
            "WFWorkflowActionParameters": {
                "WFInput": {
                    "Value": {
                        "Type": "ActionOutput",
                        "OutputName": "Dictionary",
                        "OutputUUID": "0A2F6817-7408-4FA0-BBF2-5AE34B6D26D3",
                        "Aggrandizements": [
                            {
                                "Type": "WFDictionaryValueVariableAggrandizement",
                                "DictionaryKey": "numberOfItems"
                            }
                        ]
                    },
                    "WFSerializationType": "WFTextTokenAttachment"
                },
                "UUID": "E4211B02-B874-424C-BB7B-AA06DCF4F8AD"
            }
        },
        {
            "WFWorkflowActionIdentifier": "is.workflow.actions.count",
            "WFWorkflowActionParameters": {
                "Input": {
                    "Value": {
                        "OutputUUID": "ED64FBF1-104B-4A01-B109-537FC5CB7A66",
                        "Type": "ActionOutput",
                        "OutputName": "listOfJournalPrompts"
                    },
                    "WFSerializationType": "WFTextTokenAttachment"
                },
                "UUID": "BA7529D2-83C6-4605-B54F-B708E7747D5C"
            }
        },
        {
            "WFWorkflowActionIdentifier": "is.workflow.actions.conditional",
            "WFWorkflowActionParameters": {
                "GroupingIdentifier": "840DC751-083D-40A1-98D0-D27D448EAD4D",
                "WFInput": {
                    "Type": "Variable",
                    "Variable": {
                        "Value": {
                            "OutputUUID": "E4211B02-B874-424C-BB7B-AA06DCF4F8AD",
                            "Type": "ActionOutput",
                            "OutputName": "Numbers"
                        },
                        "WFSerializationType": "WFTextTokenAttachment"
                    }
                },
                "WFControlFlowMode": 0,
                "WFNumberValue": {
                    "Value": {
                        "OutputUUID": "BA7529D2-83C6-4605-B54F-B708E7747D5C",
                        "Type": "ActionOutput",
                        "OutputName": "Count"
                    },
                    "WFSerializationType": "WFTextTokenAttachment"
                },
                "WFCondition": 0
            }
        },
        {
            "WFWorkflowActionIdentifier": "is.workflow.actions.runworkflow",
            "WFWorkflowActionParameters": {
                "WFInput": {
                    "Value": {
                        "OutputUUID": "E4211B02-B874-424C-BB7B-AA06DCF4F8AD",
                        "Type": "ActionOutput",
                        "OutputName": "Numbers"
                    },
                    "WFSerializationType": "WFTextTokenAttachment"
                },
                "CustomOutputName": "anchorIdx",
                "UUID": "78020C85-1B3F-4DEF-B115-249002D6E09A",
                "WFWorkflow": {
                    "workflowIdentifier": "1C84098A-BAB5-473C-A617-238CC3A25747",
                    "workflowName": "Random Number Generator",
                    "isSelf": false
                },
                "WFWorkflowName": "Random Number Generator"
            }
        },
        {
            "WFWorkflowActionIdentifier": "is.workflow.actions.repeat.count",
            "WFWorkflowActionParameters": {
                "GroupingIdentifier": "CC5AA86E-83C9-4210-AA77-C026113F3D3E",
                "WFRepeatCount": {
                    "Value": {
                        "OutputUUID": "E4211B02-B874-424C-BB7B-AA06DCF4F8AD",
                        "Type": "ActionOutput",
                        "OutputName": "Numbers"
                    },
                    "WFSerializationType": "WFTextTokenAttachment"
                },
                "WFControlFlowMode": 0
            }
        },
        {
            "WFWorkflowActionIdentifier": "is.workflow.actions.math",
            "WFWorkflowActionParameters": {
                "WFInput": {
                    "Value": {
                        "OutputUUID": "78020C85-1B3F-4DEF-B115-249002D6E09A",
                        "Type": "ActionOutput",
                        "OutputName": "anchorIdx"
                    },
                    "WFSerializationType": "WFTextTokenAttachment"
                },
                "WFMathOperand": {
                    "Value": {
                        "VariableName": "Repeat Index",
                        "Type": "Variable"
                    },
                    "WFSerializationType": "WFTextTokenAttachment"
                },
                "UUID": "7AE5CAA9-0860-4C87-8033-F42D407B5235"
            }
        },
        {
            "WFWorkflowActionIdentifier": "is.workflow.actions.conditional",
            "WFWorkflowActionParameters": {
                "GroupingIdentifier": "F5DA7C53-CE2C-440E-B74A-D8B184DF346A",
                "WFInput": {
                    "Type": "Variable",
                    "Variable": {
                        "Value": {
                            "OutputUUID": "7AE5CAA9-0860-4C87-8033-F42D407B5235",
                            "Type": "ActionOutput",
                            "OutputName": "Calculation Result"
                        },
                        "WFSerializationType": "WFTextTokenAttachment"
                    }
                },
                "WFControlFlowMode": 0,
                "WFNumberValue": {
                    "Value": {
                        "OutputUUID": "BA7529D2-83C6-4605-B54F-B708E7747D5C",
                        "Type": "ActionOutput",
                        "OutputName": "Count"
                    },
                    "WFSerializationType": "WFTextTokenAttachment"
                },
                "WFCondition": 4
            }
        },
        {
            "WFWorkflowActionIdentifier": "is.workflow.actions.detect.number",
            "WFWorkflowActionParameters": {
                "WFInput": {
                    "Value": {
                        "OutputUUID": "BA7529D2-83C6-4605-B54F-B708E7747D5C",
                        "Type": "ActionOutput",
                        "OutputName": "Count"
                    },
                    "WFSerializationType": "WFTextTokenAttachment"
                },
                "UUID": "A93C8451-EC28-4F91-98E0-56E2D93E63EE"
            }
        },
        {
            "WFWorkflowActionIdentifier": "is.workflow.actions.conditional",
            "WFWorkflowActionParameters": {
                "GroupingIdentifier": "F5DA7C53-CE2C-440E-B74A-D8B184DF346A",
                "WFControlFlowMode": 1
            }
        },
        {
            "WFWorkflowActionIdentifier": "is.workflow.actions.calculateexpression",
            "WFWorkflowActionParameters": {
                "Input": {
                    "Value": {
                        "string": "￼ % ￼",
                        "attachmentsByRange": {
                            "{4, 1}": {
                                "OutputUUID": "BA7529D2-83C6-4605-B54F-B708E7747D5C",
                                "Type": "ActionOutput",
                                "OutputName": "Count"
                            },
                            "{0, 1}": {
                                "OutputUUID": "7AE5CAA9-0860-4C87-8033-F42D407B5235",
                                "Type": "ActionOutput",
                                "OutputName": "Calculation Result"
                            }
                        }
                    },
                    "WFSerializationType": "WFTextTokenString"
                },
                "CustomOutputName": "module",
                "UUID": "E1825A86-A6B5-4509-AE32-8EAD76D7EF2C"
            }
        },
        {
            "WFWorkflowActionIdentifier": "is.workflow.actions.conditional",
            "WFWorkflowActionParameters": {
                "WFControlFlowMode": 2,
                "GroupingIdentifier": "F5DA7C53-CE2C-440E-B74A-D8B184DF346A",
                "UUID": "8FCBF16A-07F3-4310-A155-7695BEB6C78E"
            }
        },
        {
            "WFWorkflowActionIdentifier": "is.workflow.actions.getitemfromlist",
            "WFWorkflowActionParameters": {
                "WFInput": {
                    "Value": {
                        "OutputUUID": "ED64FBF1-104B-4A01-B109-537FC5CB7A66",
                        "Type": "ActionOutput",
                        "OutputName": "listOfJournalPrompts"
                    },
                    "WFSerializationType": "WFTextTokenAttachment"
                },
                "WFItemIndex": {
                    "Value": {
                        "OutputUUID": "8FCBF16A-07F3-4310-A155-7695BEB6C78E",
                        "Type": "ActionOutput",
                        "OutputName": "If Result"
                    },
                    "WFSerializationType": "WFTextTokenAttachment"
                },
                "UUID": "3E168EB5-91CF-40AB-8022-3D107A22C813",
                "WFItemSpecifier": "Item At Index"
            }
        },
        {
            "WFWorkflowActionIdentifier": "is.workflow.actions.repeat.count",
            "WFWorkflowActionParameters": {
                "WFControlFlowMode": 2,
                "GroupingIdentifier": "CC5AA86E-83C9-4210-AA77-C026113F3D3E",
                "UUID": "E14F7C74-59BB-47F4-B50A-B0BBB9A30054"
            }
        },
        {
            "WFWorkflowActionIdentifier": "is.workflow.actions.conditional",
            "WFWorkflowActionParameters": {
                "GroupingIdentifier": "840DC751-083D-40A1-98D0-D27D448EAD4D",
                "WFControlFlowMode": 1
            }
        },
        {
            "WFWorkflowActionIdentifier": "is.workflow.actions.detect.text",
            "WFWorkflowActionParameters": {
                "WFInput": {
                    "Value": {
                        "OutputUUID": "ED64FBF1-104B-4A01-B109-537FC5CB7A66",
                        "Type": "ActionOutput",
                        "OutputName": "listOfJournalPrompts"
                    },
                    "WFSerializationType": "WFTextTokenAttachment"
                },
                "UUID": "9BAB6ED5-0178-4C0C-9030-0739C38ABDF3"
            }
        },
        {
            "WFWorkflowActionIdentifier": "is.workflow.actions.conditional",
            "WFWorkflowActionParameters": {
                "WFControlFlowMode": 2,
                "GroupingIdentifier": "840DC751-083D-40A1-98D0-D27D448EAD4D",
                "UUID": "4ECB6D77-60B9-41CD-9D1F-5AF1EB895184"
            }
        },
        {
            "WFWorkflowActionIdentifier": "is.workflow.actions.conditional",
            "WFWorkflowActionParameters": {
                "GroupingIdentifier": "0AA4CBA2-80A0-4BE4-AD79-1D0AA0CF618C",
                "WFControlFlowMode": 1
            }
        },
        {
            "WFWorkflowActionIdentifier": "is.workflow.actions.runworkflow",
            "WFWorkflowActionParameters": {
                "WFInput": {
                    "Value": {
                        "OutputUUID": "ED64FBF1-104B-4A01-B109-537FC5CB7A66",
                        "Type": "ActionOutput",
                        "OutputName": "listOfJournalPrompts"
                    },
                    "WFSerializationType": "WFTextTokenAttachment"
                },
                "WFWorkflow": {
                    "workflowIdentifier": "E625C6C1-A183-473F-82BB-06827A38FB78",
                    "workflowName": "Get Random Item From List",
                    "isSelf": false
                },
                "UUID": "A402A0D8-D778-4A27-A7A3-A1D8FAF15EEA",
                "WFWorkflowName": "Get Random Item From List"
            }
        },
        {
            "WFWorkflowActionIdentifier": "is.workflow.actions.conditional",
            "WFWorkflowActionParameters": {
                "WFControlFlowMode": 2,
                "GroupingIdentifier": "0AA4CBA2-80A0-4BE4-AD79-1D0AA0CF618C",
                "UUID": "9D5CAA4D-2B40-47BC-8F3B-69A62A4831B7"
            }
        },
        {
            "WFWorkflowActionIdentifier": "is.workflow.actions.conditional",
            "WFWorkflowActionParameters": {
                "GroupingIdentifier": "16598923-E53C-4139-B36E-E3028925CD02",
                "WFControlFlowMode": 1
            }
        },
        {
            "WFWorkflowActionIdentifier": "is.workflow.actions.filter.reminders",
            "WFWorkflowActionParameters": {
                "WFContentItemLimitEnabled": false,
                "UUID": "60B6A12B-03A6-42C4-955A-FA292AFCC876",
                "WFContentItemLimitNumber": 5,
                "WFContentItemFilter": {
                    "Value": {
                        "WFActionParameterFilterPrefix": 1,
                        "WFContentPredicateBoundedDate": false,
                        "WFActionParameterFilterTemplates": [
                            {
                                "Operator": 4,
                                "Values": {
                                    "Enumeration": {
                                        "Value": "💭 Journal Prompts",
                                        "WFSerializationType": "WFStringSubstitutableState"
                                    }
                                },
                                "Removable": true,
                                "Property": "List"
                            },
                            {
                                "Operator": 4,
                                "Values": {
                                    "Bool": false
                                },
                                "Removable": true,
                                "Property": "Is Completed"
                            },
                            {
                                "Operator": 4,
                                "Values": {
                                    "Bool": false
                                },
                                "Removable": true,
                                "Property": "Is Flagged"
                            },
                            {
                                "Operator": 4,
                                "Values": {
                                    "Bool": true
                                },
                                "Removable": true,
                                "Property": "Has Subtasks"
                            }
                        ]
                    },
                    "WFSerializationType": "WFContentPredicateTableTemplate"
                }
            }
        },
        {
            "WFWorkflowActionIdentifier": "is.workflow.actions.repeat.each",
            "WFWorkflowActionParameters": {
                "WFInput": {
                    "Value": {
                        "OutputUUID": "60B6A12B-03A6-42C4-955A-FA292AFCC876",
                        "Type": "ActionOutput",
                        "OutputName": "Reminders"
                    },
                    "WFSerializationType": "WFTextTokenAttachment"
                },
                "GroupingIdentifier": "426507B0-2CDF-45AB-BA2F-D5438CFFB68A",
                "WFControlFlowMode": 0
            }
        },
        {
            "WFWorkflowActionIdentifier": "is.workflow.actions.properties.reminders",
            "WFWorkflowActionParameters": {
                "WFInput": {
                    "Value": {
                        "VariableName": "Repeat Item",
                        "Type": "Variable"
                    },
                    "WFSerializationType": "WFTextTokenAttachment"
                },
                "WFContentItemPropertyName": "Subtasks",
                "UUID": "D91B4845-E182-4970-BF19-E2D8FFD34D06"
            }
        },
        {
            "WFWorkflowActionIdentifier": "is.workflow.actions.repeat.each",
            "WFWorkflowActionParameters": {
                "WFControlFlowMode": 2,
                "GroupingIdentifier": "426507B0-2CDF-45AB-BA2F-D5438CFFB68A",
                "UUID": "881589E6-050F-43C4-8550-5E9B187B6642"
            }
        },
        {
            "WFWorkflowActionIdentifier": "is.workflow.actions.runworkflow",
            "WFWorkflowActionParameters": {
                "WFInput": {
                    "Value": {
                        "OutputUUID": "881589E6-050F-43C4-8550-5E9B187B6642",
                        "Type": "ActionOutput",
                        "OutputName": "Repeat Results"
                    },
                    "WFSerializationType": "WFTextTokenAttachment"
                },
                "WFWorkflow": {
                    "workflowIdentifier": "E625C6C1-A183-473F-82BB-06827A38FB78",
                    "workflowName": "Get Random Item From List",
                    "isSelf": false
                },
                "UUID": "CE367487-947E-41F4-A845-ABFC97E24D42",
                "WFWorkflowName": "Get Random Item From List"
            }
        },
        {
            "WFWorkflowActionIdentifier": "is.workflow.actions.conditional",
            "WFWorkflowActionParameters": {
                "WFControlFlowMode": 2,
                "GroupingIdentifier": "16598923-E53C-4139-B36E-E3028925CD02",
                "UUID": "A25C05CA-5D00-4309-B1F5-DAA741B6D47B"
            }
        },
        {
            "WFWorkflowActionIdentifier": "is.workflow.actions.output",
            "WFWorkflowActionParameters": {
                "WFOutput": {
                    "Value": {
                        "string": "￼",
                        "attachmentsByRange": {
                            "{0, 1}": {
                                "OutputUUID": "A25C05CA-5D00-4309-B1F5-DAA741B6D47B",
                                "Type": "ActionOutput",
                                "OutputName": "If Result"
                            }
                        }
                    },
                    "WFSerializationType": "WFTextTokenString"
                }
            }
        }
    ],
    "WFWorkflowInputContentItemClasses": [
        "WFStringContentItem"
    ],
    "WFWorkflowImportQuestions": [],
    "WFWorkflowTypes": [],
    "WFQuickActionSurfaces": [],
    "WFWorkflowHasShortcutInputVariables": true
}